README.md
setup.py
suning/__init__.py
suning/api/__init__.py
suning/api/abstract.py
suning/api/config.py
suning/api/advertise/BaojieapiQueryRequest.py
suning/api/advertise/BjcpcunitdetailQueryRequest.py
suning/api/advertise/BjcpmQueryRequest.py
suning/api/advertise/BjcpmmurlGetRequest.py
suning/api/advertise/BjcptQueryRequest.py
suning/api/advertise/BjcptmurlGetRequest.py
suning/api/advertise/PromAccountBalanceGetRequest.py
suning/api/advertise/PromCatalogReportsGetRequest.py
suning/api/advertise/PromKeywordMarketQueryRequest.py
suning/api/advertise/PromKeywordReportsQueryRequest.py
suning/api/advertise/PromPlanManageAddRequest.py
suning/api/advertise/PromPlanReportsGetRequest.py
suning/api/advertise/PromRelateKeywordGetRequest.py
suning/api/advertise/PromUnitManageAddRequest.py
suning/api/advertise/PromUnitReportsGetRequest.py
suning/api/advertise/PromotionDiscountModifyRequest.py
suning/api/advertise/PromotionEndDateModifyRequest.py
suning/api/advertise/PromotionLimitModifyRequest.py
suning/api/advertise/PromotionPlanAddRequest.py
suning/api/advertise/PromotionPlanGetRequest.py
suning/api/advertise/PromotionPlanQueryRequest.py
suning/api/advertise/PromotionUnitAddRequest.py
suning/api/advertise/PromotionUnitGetRequest.py
suning/api/advertise/PromotionUnitModifyRequest.py
suning/api/advertise/PromotionUnitQueryRequest.py
suning/api/advertise/SearchReportsGetRequest.py
suning/api/advertise/__init__.py
suning/api/advertise/pPromUnitReportsGetRequest.py
suning/api/asmp/DispatchOrderAddRequest.py
suning/api/asmp/SnInstallOrderAddRequest.py
suning/api/asmp/StatementGetRequest.py
suning/api/asmp/__init__.py
suning/api/buyout/AddressQueryRequest.py
suning/api/buyout/CitysrcQueryRequest.py
suning/api/buyout/CountysrcQueryRequest.py
suning/api/buyout/LgsstatusQueryRequest.py
suning/api/buyout/MessagecallbackReceiveRequest.py
suning/api/buyout/MessagenotifyQueryRequest.py
suning/api/buyout/OrderCancelRequest.py
suning/api/buyout/OrderCreateRequest.py
suning_sdk.egg-info/PKG-INFO
suning_sdk.egg-info/SOURCES.txt
suning_sdk.egg-info/dependency_links.txt
suning_sdk.egg-info/top_level.txt