Metadata-Version: 2.1
Name: suning-sdk
Version: 1.0.0
Summary: suning-sdk from suning open platform
Home-page: https://github.com/why2lyj/suning-sdk
Author: Snow Wang
Author-email: admin@farseer.vip
License: MIT Licence
Keywords: pip,suning,suning-sdk
Platform: any
